i18trans/__init__.py
i18trans/__main__.py
i18trans/config.py
i18trans/ui.py
i18trans-0.0.3.dist-info/METADATA
i18trans-0.0.3.dist-info/WHEEL
i18trans-0.0.3.dist-info/entry_points.txt
i18trans-0.0.3.dist-info/top_level.txt
i18trans-0.0.3.dist-info/RECORD
