Metadata-Version: 2.2
Name: i18trans
Version: 0.0.3
Home-page: https://www.codehemu.com/p/jsontrans.html
Author: Hemanta Gayen
License: MIT
Project-URL: Source Code, https://github.com/hemucode/i18trans
Project-URL: Bug Tracker, https://github.com/hemucode/i18trans/issues
Project-URL: Changelog, https://github.com/hemucode/i18trans/blob/master/CHANGELOG.md
Keywords: gui,executable
Classifier: License :: OSI Approved :: MIT License
Classifier: Programming Language :: Python
Classifier: Programming Language :: Python :: 3
Classifier: Programming Language :: Python :: 3.6
Classifier: Programming Language :: Python :: 3.7
Classifier: Programming Language :: Python :: 3.8
Classifier: Programming Language :: Python :: 3.9
Classifier: Programming Language :: Python :: 3.10
Classifier: Programming Language :: Python :: 3.11
Classifier: Programming Language :: Python :: 3.12
Classifier: Programming Language :: Python :: 3.13
Classifier: Operating System :: Microsoft :: Windows
Classifier: Operating System :: POSIX :: Linux
Requires-Dist: tk>=0.1.0
Requires-Dist: googletrans==4.0.0-rc1
Dynamic: author
Dynamic: classifier
Dynamic: description
Dynamic: description-content-type
Dynamic: home-page
Dynamic: keywords
Dynamic: license
Dynamic: project-url
Dynamic: requires-dist
